feetech_client/__init__.py
feetech_client/bus.py
feetech_client/main.py
feetech_client-0.1.dist-info/METADATA
feetech_client-0.1.dist-info/WHEEL
feetech_client-0.1.dist-info/entry_points.txt
feetech_client-0.1.dist-info/RECORD
