Metadata-Version: 2.3
Name: feetech-client
Version: 0.1
Summary: Dora Node client for feetech motors.
License: MIT
Author: Hennzau
Author-email: <dev@enzo-le-van.fr>
Requires-Python: >=3.9
Classifier: License :: OSI Approved :: MIT License
Classifier: Programming Language :: Python :: 3
Classifier: Programming Language :: Python :: 3.9
Classifier: Programming Language :: Python :: 3.10
Classifier: Programming Language :: Python :: 3.11
Classifier: Programming Language :: Python :: 3.12
Classifier: Programming Language :: Python :: 3.13
Requires-Dist: dora-rs (==0.3.5)
Requires-Dist: feetech-servo-sdk (==1.0.0)
Requires-Dist: numpy (<=2.0.0)
